{
  "type": "section_content",
  "slides": [
    {
      "type": "section",
      "purpose": "section_header"
    },
    {
      "type": "title",
      "purpose": "content"
    },
    {
      "type": "agenda",
      "purpose": "content"
    },
    {
      "type": "title",
      "purpose": "content"
    },
    {
      "type": "summary",
      "purpose": "content"
    },
    {
      "type": "summary",
      "purpose": "content"
    },
    {
      "type": "summary",
      "purpose": "content"
    },
    {
      "type": "summary",
      "purpose": "content"
    },
    {
      "type": "title",
      "purpose": "content"
    },
    {
      "type": "detail",
      "purpose": "content"
    },
    {
      "type": "content",
      "purpose": "content"
    },
    {
      "type": "content",
      "purpose": "content"
    },
    {
      "type": "title",
      "purpose": "content"
    },
    {
      "type": "content",
      "purpose": "content"
    },
    {
      "type": "content",
      "purpose": "content"
    },
    {
      "type": "content",
      "purpose": "content"
    },
    {
      "type": "detail",
      "purpose": "content"
    },
    {
      "type": "content",
      "purpose": "content"
    },
    {
      "type": "content",
      "purpose": "content"
    },
    {
      "type": "content",
      "purpose": "content"
    }
  ],
  "length": 20,
  "template": "template_market_analysis",
  "id": "7e045b132cfb"
}