{
  "id": "348ffe973494",
  "template": "template_business_case",
  "slide_num": 210,
  "layout_name": "Default",
  "element_count": 22,
  "elements": [
    {
      "shape_type": "PLACEHOLDER (14)",
      "category": "other",
      "position": {
        "left": 0.0455,
        "top": 0.0518,
        "width": 0.909,
        "height": 0.1067,
        "right": 0.9545,
        "bottom": 0.1584
      },
      "position_inches": {
        "left": 0.61,
        "top": 0.39,
        "width": 12.12,
        "height": 0.8
      },
      "zone": "top_center",
      "has_text": true,
      "text_sample": "Project costs: Costs are mainly tied to software l"
    },
    {
      "shape_type": "PLACEHOLDER (14)",
      "category": "other",
      "position": {
        "left": 0.0455,
        "top": 0.1923,
        "width": 0.909,
        "height": 0.0404,
        "right": 0.9545,
        "bottom": 0.2327
      },
      "position_inches": {
        "left": 0.61,
        "top": 1.44,
        "width": 12.12,
        "height": 0.3
      },
      "zone": "middle_center",
      "has_text": false
    },
    {
      "shape_type": "PLACEHOLDER (14)",
      "category": "other",
      "position": {
        "left": 0.6258,
        "top": 0.0147,
        "width": 0.3287,
        "height": 0.018,
        "right": 0.9545,
        "bottom": 0.0326
      },
      "position_inches": {
        "left": 8.34,
        "top": 0.11,
        "width": 4.38,
        "height": 0.13
      },
      "zone": "top_right",
      "has_text": false
    },
    {
      "shape_type": "TEXT_BOX (17)",
      "category": "other",
      "position": {
        "left": 0.0455,
        "top": 0.1923,
        "width": 0.909,
        "height": 0.0404,
        "right": 0.9545,
        "bottom": 0.2327
      },
      "position_inches": {
        "left": 0.61,
        "top": 1.44,
        "width": 12.12,
        "height": 0.3
      },
      "zone": "middle_center",
      "has_text": false
    },
    {
      "shape_type": "AUTO_SHAPE (1)",
      "category": "other",
      "position": {
        "left": 0.0455,
        "top": 0.3893,
        "width": 0.1868,
        "height": 0.1927,
        "right": 0.2323,
        "bottom": 0.582
      },
      "position_inches": {
        "left": 0.61,
        "top": 2.92,
        "width": 2.49,
        "height": 1.45
      },
      "zone": "middle_left",
      "has_text": true,
      "text_sample": "Software"
    },
    {
      "shape_type": "AUTO_SHAPE (1)",
      "category": "other",
      "position": {
        "left": 0.0455,
        "top": 0.6044,
        "width": 0.1868,
        "height": 0.0771,
        "right": 0.2323,
        "bottom": 0.6815
      },
      "position_inches": {
        "left": 0.61,
        "top": 4.53,
        "width": 2.49,
        "height": 0.58
      },
      "zone": "middle_left",
      "has_text": true,
      "text_sample": "Hardware"
    },
    {
      "shape_type": "AUTO_SHAPE (1)",
      "category": "other",
      "position": {
        "left": 0.0455,
        "top": 0.7039,
        "width": 0.1868,
        "height": 0.0771,
        "right": 0.2323,
        "bottom": 0.7809
      },
      "position_inches": {
        "left": 0.61,
        "top": 5.28,
        "width": 2.49,
        "height": 0.58
      },
      "zone": "middle_left",
      "has_text": true,
      "text_sample": "Personnel"
    },
    {
      "shape_type": "AUTO_SHAPE (1)",
      "category": "other",
      "position": {
        "left": 0.0455,
        "top": 0.8033,
        "width": 0.1868,
        "height": 0.0771,
        "right": 0.2323,
        "bottom": 0.8804
      },
      "position_inches": {
        "left": 0.61,
        "top": 6.02,
        "width": 2.49,
        "height": 0.58
      },
      "zone": "bottom_left",
      "has_text": true,
      "text_sample": "Services"
    },
    {
      "shape_type": "AUTO_SHAPE (1)",
      "category": "other",
      "position": {
        "left": 0.2455,
        "top": 0.2899,
        "width": 0.343,
        "height": 0.0771,
        "right": 0.5885,
        "bottom": 0.3669
      },
      "position_inches": {
        "left": 3.27,
        "top": 2.17,
        "width": 4.57,
        "height": 0.58
      },
      "zone": "middle_center",
      "has_text": true,
      "text_sample": "Acquisition and ramp up phase"
    },
    {
      "shape_type": "AUTO_SHAPE (1)",
      "category": "other",
      "position": {
        "left": 0.6115,
        "top": 0.2899,
        "width": 0.343,
        "height": 0.0771,
        "right": 0.9545,
        "bottom": 0.3669
      },
      "position_inches": {
        "left": 8.15,
        "top": 2.17,
        "width": 4.57,
        "height": 0.58
      },
      "zone": "middle_right",
      "has_text": true,
      "text_sample": "Operational phase"
    },
    {
      "shape_type": "AUTO_SHAPE (1)",
      "category": "other",
      "position": {
        "left": 0.2455,
        "top": 0.3893,
        "width": 0.343,
        "height": 0.1927,
        "right": 0.5885,
        "bottom": 0.582
      },
      "position_inches": {
        "left": 3.27,
        "top": 2.92,
        "width": 4.57,
        "height": 1.45
      },
      "zone": "middle_center",
      "has_text": true,
      "text_sample": "One-time license for data module One-time license"
    },
    {
      "shape_type": "AUTO_SHAPE (1)",
      "category": "other",
      "position": {
        "left": 0.2455,
        "top": 0.6044,
        "width": 0.343,
        "height": 0.0771,
        "right": 0.5885,
        "bottom": 0.6815
      },
      "position_inches": {
        "left": 3.27,
        "top": 4.53,
        "width": 4.57,
        "height": 0.58
      },
      "zone": "middle_center",
      "has_text": true,
      "text_sample": "Server system upgrade Some transfer to cloud"
    },
    {
      "shape_type": "AUTO_SHAPE (1)",
      "category": "other",
      "position": {
        "left": 0.2455,
        "top": 0.7039,
        "width": 0.343,
        "height": 0.0771,
        "right": 0.5885,
        "bottom": 0.7809
      },
      "position_inches": {
        "left": 3.27,
        "top": 5.28,
        "width": 4.57,
        "height": 0.58
      },
      "zone": "middle_center",
      "has_text": true,
      "text_sample": "Initial training Hire 1-2 FTEs"
    },
    {
      "shape_type": "AUTO_SHAPE (1)",
      "category": "other",
      "position": {
        "left": 0.2455,
        "top": 0.8033,
        "width": 0.343,
        "height": 0.0771,
        "right": 0.5885,
        "bottom": 0.8804
      },
      "position_inches": {
        "left": 3.27,
        "top": 6.02,
        "width": 4.57,
        "height": 0.58
      },
      "zone": "bottom_center",
      "has_text": true,
      "text_sample": "Installation and integration services from provide"
    },
    {
      "shape_type": "AUTO_SHAPE (1)",
      "category": "other",
      "position": {
        "left": 0.6115,
        "top": 0.3893,
        "width": 0.343,
        "height": 0.1927,
        "right": 0.9545,
        "bottom": 0.582
      },
      "position_inches": {
        "left": 8.15,
        "top": 2.92,
        "width": 4.57,
        "height": 1.45
      },
      "zone": "middle_right",
      "has_text": true,
      "text_sample": "Maintenance costs Package upgrades, when relevant"
    },
    {
      "shape_type": "AUTO_SHAPE (1)",
      "category": "other",
      "position": {
        "left": 0.6115,
        "top": 0.6044,
        "width": 0.343,
        "height": 0.0771,
        "right": 0.9545,
        "bottom": 0.6815
      },
      "position_inches": {
        "left": 8.15,
        "top": 4.53,
        "width": 4.57,
        "height": 0.58
      },
      "zone": "middle_right",
      "has_text": true,
      "text_sample": "Server system upgrades"
    },
    {
      "shape_type": "AUTO_SHAPE (1)",
      "category": "other",
      "position": {
        "left": 0.6115,
        "top": 0.7039,
        "width": 0.343,
        "height": 0.0771,
        "right": 0.9545,
        "bottom": 0.7809
      },
      "position_inches": {
        "left": 8.15,
        "top": 5.28,
        "width": 4.57,
        "height": 0.58
      },
      "zone": "middle_right",
      "has_text": true,
      "text_sample": "Continuous training of experienced and new hires"
    },
    {
      "shape_type": "AUTO_SHAPE (1)",
      "category": "other",
      "position": {
        "left": 0.6115,
        "top": 0.8033,
        "width": 0.343,
        "height": 0.0771,
        "right": 0.9545,
        "bottom": 0.8804
      },
      "position_inches": {
        "left": 8.15,
        "top": 6.02,
        "width": 4.57,
        "height": 0.58
      },
      "zone": "bottom_right",
      "has_text": true,
      "text_sample": "SLA"
    },
    {
      "shape_type": "LINE (9)",
      "category": "other",
      "position": {
        "left": 0.0455,
        "top": 0.5932,
        "width": 0.909,
        "height": 0.0,
        "right": 0.9545,
        "bottom": 0.5932
      },
      "position_inches": {
        "left": 0.61,
        "top": 4.45,
        "width": 12.12,
        "height": 0.0
      },
      "zone": "middle_center",
      "has_text": false
    },
    {
      "shape_type": "LINE (9)",
      "category": "other",
      "position": {
        "left": 0.0455,
        "top": 0.6927,
        "width": 0.909,
        "height": 0.0,
        "right": 0.9545,
        "bottom": 0.6927
      },
      "position_inches": {
        "left": 0.61,
        "top": 5.2,
        "width": 12.12,
        "height": 0.0
      },
      "zone": "middle_center",
      "has_text": false
    },
    {
      "shape_type": "LINE (9)",
      "category": "other",
      "position": {
        "left": 0.0455,
        "top": 0.7921,
        "width": 0.909,
        "height": 0.0,
        "right": 0.9545,
        "bottom": 0.7921
      },
      "position_inches": {
        "left": 0.61,
        "top": 5.94,
        "width": 12.12,
        "height": 0.0
      },
      "zone": "middle_center",
      "has_text": false
    },
    {
      "shape_type": "TEXT_BOX (17)",
      "category": "other",
      "position": {
        "left": 0.0384,
        "top": 0.9319,
        "width": 0.5984,
        "height": 0.0532,
        "right": 0.6368,
        "bottom": 0.9852
      },
      "position_inches": {
        "left": 0.51,
        "top": 6.99,
        "width": 7.98,
        "height": 0.4
      },
      "zone": "bottom_center",
      "has_text": true,
      "text_sample": "Source: Team analysis"
    }
  ],
  "zones": [
    {
      "name": "top_center",
      "bounds": {
        "left": 0.0455,
        "top": 0.0518,
        "right": 0.9545,
        "bottom": 0.1584,
        "width": 0.909,
        "height": 0.1066
      },
      "element_count": 1,
      "primary_content": "other"
    },
    {
      "name": "middle_center",
      "bounds": {
        "left": 0.0455,
        "top": 0.1923,
        "right": 0.9545,
        "bottom": 0.7921,
        "width": 0.909,
        "height": 0.5998
      },
      "element_count": 9,
      "primary_content": "other"
    },
    {
      "name": "top_right",
      "bounds": {
        "left": 0.6258,
        "top": 0.0147,
        "right": 0.9545,
        "bottom": 0.0326,
        "width": 0.3287,
        "height": 0.0179
      },
      "element_count": 1,
      "primary_content": "other"
    },
    {
      "name": "middle_left",
      "bounds": {
        "left": 0.0455,
        "top": 0.3893,
        "right": 0.2323,
        "bottom": 0.7809,
        "width": 0.1868,
        "height": 0.3916
      },
      "element_count": 3,
      "primary_content": "other"
    },
    {
      "name": "bottom_left",
      "bounds": {
        "left": 0.0455,
        "top": 0.8033,
        "right": 0.2323,
        "bottom": 0.8804,
        "width": 0.1868,
        "height": 0.0771
      },
      "element_count": 1,
      "primary_content": "other"
    },
    {
      "name": "middle_right",
      "bounds": {
        "left": 0.6115,
        "top": 0.2899,
        "right": 0.9545,
        "bottom": 0.7809,
        "width": 0.343,
        "height": 0.491
      },
      "element_count": 4,
      "primary_content": "other"
    },
    {
      "name": "bottom_center",
      "bounds": {
        "left": 0.0384,
        "top": 0.8033,
        "right": 0.6368,
        "bottom": 0.9852,
        "width": 0.5984,
        "height": 0.1819
      },
      "element_count": 2,
      "primary_content": "other"
    },
    {
      "name": "bottom_right",
      "bounds": {
        "left": 0.6115,
        "top": 0.8033,
        "right": 0.9545,
        "bottom": 0.8804,
        "width": 0.343,
        "height": 0.0771
      },
      "element_count": 1,
      "primary_content": "other"
    }
  ],
  "margins": {
    "left": 0.0384,
    "right": 0.0455,
    "top": 0.0147,
    "bottom": 0.0148,
    "left_inches": 0.51,
    "right_inches": 0.61,
    "top_inches": 0.11,
    "bottom_inches": 0.11
  },
  "content_types": {
    "other": 22
  },
  "category": "multi_column"
}