{
  "id": "637ef30ad44e",
  "template": "pptx_template_due_diligence",
  "slide_num": 174,
  "layout_name": "Default",
  "element_count": 8,
  "elements": [
    {
      "shape_type": "EMBEDDED_OLE_OBJECT (7)",
      "category": "other",
      "position": {
        "left": 0.0001,
        "top": 0.0002,
        "width": 0.0001,
        "height": 0.0002,
        "right": 0.0002,
        "bottom": 0.0005
      },
      "position_inches": {
        "left": 0.0,
        "top": 0.0,
        "width": 0.0,
        "height": 0.0
      },
      "zone": "top_left",
      "has_text": false
    },
    {
      "shape_type": "PLACEHOLDER (14)",
      "category": "other",
      "position": {
        "left": 0.0455,
        "top": 0.0518,
        "width": 0.909,
        "height": 0.1067,
        "right": 0.9545,
        "bottom": 0.1584
      },
      "position_inches": {
        "left": 0.61,
        "top": 0.39,
        "width": 12.12,
        "height": 0.8
      },
      "zone": "top_center",
      "has_text": true,
      "text_sample": "There is potential for ~27 new [Target] stores if"
    },
    {
      "shape_type": "PLACEHOLDER (14)",
      "category": "other",
      "position": {
        "left": 0.6258,
        "top": 0.0147,
        "width": 0.3287,
        "height": 0.018,
        "right": 0.9545,
        "bottom": 0.0326
      },
      "position_inches": {
        "left": 8.34,
        "top": 0.11,
        "width": 4.38,
        "height": 0.13
      },
      "zone": "top_right",
      "has_text": true,
      "text_sample": "Real-life sanitized example #1"
    },
    {
      "shape_type": "TEXT_BOX (17)",
      "category": "other",
      "position": {
        "left": 0.0455,
        "top": 0.9484,
        "width": 0.909,
        "height": 0.0202,
        "right": 0.9545,
        "bottom": 0.9686
      },
      "position_inches": {
        "left": 0.61,
        "top": 7.11,
        "width": 12.12,
        "height": 0.15
      },
      "zone": "bottom_center",
      "has_text": true,
      "text_sample": "Source: [Target] homepage; Statistics Germany; [Co"
    },
    {
      "shape_type": "CHART (3)",
      "category": "other",
      "position": {
        "left": 0.0449,
        "top": 0.3351,
        "width": 0.6667,
        "height": 0.5704,
        "right": 0.7116,
        "bottom": 0.9056
      },
      "position_inches": {
        "left": 0.6,
        "top": 2.51,
        "width": 8.89,
        "height": 4.28
      },
      "zone": "middle_center",
      "has_text": false
    },
    {
      "shape_type": "TEXT_BOX (17)",
      "category": "other",
      "position": {
        "left": 0.6644,
        "top": 0.5271,
        "width": 0.1285,
        "height": 0.0364,
        "right": 0.7928,
        "bottom": 0.5636
      },
      "position_inches": {
        "left": 8.86,
        "top": 3.95,
        "width": 1.71,
        "height": 0.27
      },
      "zone": "middle_right",
      "has_text": false
    },
    {
      "shape_type": "TEXT_BOX (17)",
      "category": "other",
      "position": {
        "left": 0.7602,
        "top": 0.3658,
        "width": 0.1934,
        "height": 0.359,
        "right": 0.9536,
        "bottom": 0.7249
      },
      "position_inches": {
        "left": 10.14,
        "top": 2.74,
        "width": 2.58,
        "height": 2.69
      },
      "zone": "middle_right",
      "has_text": true,
      "text_sample": "There is potential for ~27 new [Target] stores if"
    },
    {
      "shape_type": "AUTO_SHAPE (1)",
      "category": "other",
      "position": {
        "left": 0.0384,
        "top": 0.2325,
        "width": 0.6732,
        "height": 0.0763,
        "right": 0.7116,
        "bottom": 0.3088
      },
      "position_inches": {
        "left": 0.51,
        "top": 1.74,
        "width": 8.98,
        "height": 0.57
      },
      "zone": "middle_center",
      "has_text": true,
      "text_sample": "Current [Target] stores and potential new [Target]"
    }
  ],
  "zones": [
    {
      "name": "top_left",
      "bounds": {
        "left": 0.0001,
        "top": 0.0002,
        "right": 0.0002,
        "bottom": 0.0005,
        "width": 0.0001,
        "height": 0.0003
      },
      "element_count": 1,
      "primary_content": "other"
    },
    {
      "name": "top_center",
      "bounds": {
        "left": 0.0455,
        "top": 0.0518,
        "right": 0.9545,
        "bottom": 0.1584,
        "width": 0.909,
        "height": 0.1066
      },
      "element_count": 1,
      "primary_content": "other"
    },
    {
      "name": "top_right",
      "bounds": {
        "left": 0.6258,
        "top": 0.0147,
        "right": 0.9545,
        "bottom": 0.0326,
        "width": 0.3287,
        "height": 0.0179
      },
      "element_count": 1,
      "primary_content": "other"
    },
    {
      "name": "bottom_center",
      "bounds": {
        "left": 0.0455,
        "top": 0.9484,
        "right": 0.9545,
        "bottom": 0.9686,
        "width": 0.909,
        "height": 0.0202
      },
      "element_count": 1,
      "primary_content": "other"
    },
    {
      "name": "middle_center",
      "bounds": {
        "left": 0.0384,
        "top": 0.2325,
        "right": 0.7116,
        "bottom": 0.9056,
        "width": 0.6732,
        "height": 0.6731
      },
      "element_count": 2,
      "primary_content": "other"
    },
    {
      "name": "middle_right",
      "bounds": {
        "left": 0.6644,
        "top": 0.3658,
        "right": 0.9536,
        "bottom": 0.7249,
        "width": 0.2892,
        "height": 0.3591
      },
      "element_count": 2,
      "primary_content": "other"
    }
  ],
  "margins": {
    "left": 0.0001,
    "right": 0.0455,
    "top": 0.0002,
    "bottom": 0.0314,
    "left_inches": 0.0,
    "right_inches": 0.61,
    "top_inches": 0.0,
    "bottom_inches": 0.24
  },
  "content_types": {
    "other": 8
  },
  "category": "mixed_content"
}