{
  "id": "842cce310198",
  "template": "pptx_template_due_diligence",
  "slide_num": 35,
  "layout_name": "Agenda",
  "element_count": 11,
  "elements": [
    {
      "shape_type": "PLACEHOLDER (14)",
      "category": "other",
      "position": {
        "left": 0.0385,
        "top": 0.2423,
        "width": 0.2464,
        "height": 0.1183,
        "right": 0.285,
        "bottom": 0.3606
      },
      "position_inches": {
        "left": 0.51,
        "top": 1.82,
        "width": 3.29,
        "height": 0.89
      },
      "zone": "middle_left",
      "has_text": true,
      "text_sample": "Content"
    },
    {
      "shape_type": "PLACEHOLDER (14)",
      "category": "other",
      "position": {
        "left": 0.4094,
        "top": 0.2423,
        "width": 0.5454,
        "height": 0.6484,
        "right": 0.9548,
        "bottom": 0.8906
      },
      "position_inches": {
        "left": 5.46,
        "top": 1.82,
        "width": 7.27,
        "height": 4.86
      },
      "zone": "middle_right",
      "has_text": true,
      "text_sample": "[Insert content section] [Insert content section]"
    },
    {
      "shape_type": "AUTO_SHAPE (1)",
      "category": "other",
      "position": {
        "left": 0.4161,
        "top": 0.2693,
        "width": 0.03,
        "height": 0.0533,
        "right": 0.4461,
        "bottom": 0.3226
      },
      "position_inches": {
        "left": 5.55,
        "top": 2.02,
        "width": 0.4,
        "height": 0.4
      },
      "zone": "middle_center",
      "has_text": true,
      "text_sample": "1"
    },
    {
      "shape_type": "AUTO_SHAPE (1)",
      "category": "other",
      "position": {
        "left": 0.4161,
        "top": 0.3375,
        "width": 0.03,
        "height": 0.0533,
        "right": 0.4461,
        "bottom": 0.3908
      },
      "position_inches": {
        "left": 5.55,
        "top": 2.53,
        "width": 0.4,
        "height": 0.4
      },
      "zone": "middle_center",
      "has_text": true,
      "text_sample": "2"
    },
    {
      "shape_type": "AUTO_SHAPE (1)",
      "category": "other",
      "position": {
        "left": 0.4161,
        "top": 0.4056,
        "width": 0.03,
        "height": 0.0533,
        "right": 0.4461,
        "bottom": 0.4589
      },
      "position_inches": {
        "left": 5.55,
        "top": 3.04,
        "width": 0.4,
        "height": 0.4
      },
      "zone": "middle_center",
      "has_text": true,
      "text_sample": "3"
    },
    {
      "shape_type": "AUTO_SHAPE (1)",
      "category": "other",
      "position": {
        "left": 0.4161,
        "top": 0.4738,
        "width": 0.03,
        "height": 0.0533,
        "right": 0.4461,
        "bottom": 0.5271
      },
      "position_inches": {
        "left": 5.55,
        "top": 3.55,
        "width": 0.4,
        "height": 0.4
      },
      "zone": "middle_center",
      "has_text": true,
      "text_sample": "4"
    },
    {
      "shape_type": "AUTO_SHAPE (1)",
      "category": "other",
      "position": {
        "left": 0.4161,
        "top": 0.5419,
        "width": 0.03,
        "height": 0.0533,
        "right": 0.4461,
        "bottom": 0.5952
      },
      "position_inches": {
        "left": 5.55,
        "top": 4.06,
        "width": 0.4,
        "height": 0.4
      },
      "zone": "middle_center",
      "has_text": true,
      "text_sample": "5"
    },
    {
      "shape_type": "AUTO_SHAPE (1)",
      "category": "other",
      "position": {
        "left": 0.4161,
        "top": 0.6101,
        "width": 0.03,
        "height": 0.0533,
        "right": 0.4461,
        "bottom": 0.6634
      },
      "position_inches": {
        "left": 5.55,
        "top": 4.58,
        "width": 0.4,
        "height": 0.4
      },
      "zone": "middle_center",
      "has_text": true,
      "text_sample": "6"
    },
    {
      "shape_type": "AUTO_SHAPE (1)",
      "category": "other",
      "position": {
        "left": 0.4161,
        "top": 0.6782,
        "width": 0.03,
        "height": 0.0533,
        "right": 0.4461,
        "bottom": 0.7315
      },
      "position_inches": {
        "left": 5.55,
        "top": 5.09,
        "width": 0.4,
        "height": 0.4
      },
      "zone": "middle_center",
      "has_text": true,
      "text_sample": "7"
    },
    {
      "shape_type": "AUTO_SHAPE (1)",
      "category": "other",
      "position": {
        "left": 0.4161,
        "top": 0.7464,
        "width": 0.03,
        "height": 0.0533,
        "right": 0.4461,
        "bottom": 0.7997
      },
      "position_inches": {
        "left": 5.55,
        "top": 5.6,
        "width": 0.4,
        "height": 0.4
      },
      "zone": "middle_center",
      "has_text": true,
      "text_sample": "8"
    },
    {
      "shape_type": "AUTO_SHAPE (1)",
      "category": "other",
      "position": {
        "left": 0.4161,
        "top": 0.8145,
        "width": 0.03,
        "height": 0.0533,
        "right": 0.4461,
        "bottom": 0.8679
      },
      "position_inches": {
        "left": 5.55,
        "top": 6.11,
        "width": 0.4,
        "height": 0.4
      },
      "zone": "bottom_center",
      "has_text": true,
      "text_sample": "9"
    }
  ],
  "zones": [
    {
      "name": "middle_left",
      "bounds": {
        "left": 0.0385,
        "top": 0.2423,
        "right": 0.285,
        "bottom": 0.3606,
        "width": 0.2465,
        "height": 0.1183
      },
      "element_count": 1,
      "primary_content": "other"
    },
    {
      "name": "middle_right",
      "bounds": {
        "left": 0.4094,
        "top": 0.2423,
        "right": 0.9548,
        "bottom": 0.8906,
        "width": 0.5454,
        "height": 0.6483
      },
      "element_count": 1,
      "primary_content": "other"
    },
    {
      "name": "middle_center",
      "bounds": {
        "left": 0.4161,
        "top": 0.2693,
        "right": 0.4461,
        "bottom": 0.7997,
        "width": 0.03,
        "height": 0.5304
      },
      "element_count": 8,
      "primary_content": "other"
    },
    {
      "name": "bottom_center",
      "bounds": {
        "left": 0.4161,
        "top": 0.8145,
        "right": 0.4461,
        "bottom": 0.8679,
        "width": 0.03,
        "height": 0.0534
      },
      "element_count": 1,
      "primary_content": "other"
    }
  ],
  "margins": {
    "left": 0.0385,
    "right": 0.0452,
    "top": 0.2423,
    "bottom": 0.1094,
    "left_inches": 0.51,
    "right_inches": 0.6,
    "top_inches": 1.82,
    "bottom_inches": 0.82
  },
  "content_types": {
    "other": 11
  },
  "category": "multi_column"
}